dnslib/__init__.py
dnslib/bimap.py
dnslib/bit.py
dnslib/buffer.py
dnslib/client.py
dnslib/digparser.py
dnslib/dns.py
dnslib/fixedresolver.py
dnslib/intercept.py
dnslib/label.py
dnslib/lex.py
dnslib/proxy.py
dnslib/ranges.py
dnslib/server.py
dnslib/shellresolver.py
dnslib/test/1.1.1.1.in-addr.arpa.-PTR
dnslib/test/8.8.8.8.in-addr.arpa.-PTR
dnslib/test/9.9.9.9.in-addr.arpa.-PTR
dnslib/test/ECC94C1D-7026-41AA-B47E-FDFE40EB9957.com-A
dnslib/test/_sip._udp.sipgate.co.uk-SRV
dnslib/test/cloudflare.com-A
dnslib/test/cloudflare.com-A-dnssec
dnslib/test/cloudflare.com-AAAA
dnslib/test/cloudflare.com-AAAA-dnssec
dnslib/test/cloudflare.com-CNAME
dnslib/test/cloudflare.com-CNAME-dnssec
dnslib/test/cloudflare.com-MX
dnslib/test/cloudflare.com-MX-dnssec
dnslib/test/cloudflare.com-NS
dnslib/test/cloudflare.com-NS-dnssec
dnslib/test/cloudflare.com-SOA
dnslib/test/cloudflare.com-SOA-dnssec
dnslib/test/cloudflare.com-TXT
dnslib/test/cloudflare.com-TXT-dnssec
dnslib/test/dig/google.com-A.dig
dnslib/test/dig/google.com-ANY.dig
dnslib/test/example.org-DNSKEY
dnslib/test/example.org-DS
dnslib/test/example.org-MX-dnssec
dnslib/test/example.org-PTR-dnssec
dnslib/test/example.org-SOA-dnssec
dnslib/test/fedoraproject.org-TLSA
dnslib/test/google.com-MX
dnslib/test/google.com-NS
dnslib/test/google.com-SOA
dnslib/test/google.com-TXT
dnslib/test/he.net-MX
dnslib/test/he.net-NS
dnslib/test/he.net-SOA
dnslib/test/he.net-TXT
dnslib/test/iana.org-A
dnslib/test/iana.org-A-dnssec
dnslib/test/iana.org-AAAA
dnslib/test/iana.org-AAAA-dnssec
dnslib/test/iana.org-DNSKEY
dnslib/test/iana.org-MX
dnslib/test/iana.org-MX-dnssec
dnslib/test/iana.org-NS
dnslib/test/iana.org-NS-dnssec
dnslib/test/iana.org-PTR-dnssec
dnslib/test/iana.org-SOA
dnslib/test/iana.org-SOA-dnssec
dnslib/test/iana.org-TXT
dnslib/test/iana.org-TXT-dnssec
dnslib/test/oilpro.ch-TYPE65534
dnslib/test/openssl.org-TLSA
dnslib/test/salsa.debian.org-SSHFP
dnslib/test/sip2sip.info-NAPTR
dnslib/test/www.example.org-A-dnssec
dnslib3-0.10.0.dist-info/LICENSE
dnslib3-0.10.0.dist-info/METADATA
dnslib3-0.10.0.dist-info/WHEEL
dnslib3-0.10.0.dist-info/RECORD
