Metadata-Version: 2.1
Name: dnslib3
Version: 0.10.0
Summary: Simple library to encode/decode DNS wire-format packets
License: BSD-2-Clause
Author: Paul Chakravarti
Requires-Python: >=3.8,<4.0
Classifier: License :: OSI Approved :: BSD License
Classifier: Programming Language :: Python :: 3
Classifier: Programming Language :: Python :: 3.8
Classifier: Programming Language :: Python :: 3.9
Classifier: Programming Language :: Python :: 3.10
Classifier: Programming Language :: Python :: 3.11
Classifier: Programming Language :: Python :: 3.12
Classifier: Topic :: Internet :: Name Service (DNS)
